sqlraw/__init__.py
sqlraw/sqlraw.py
sqlraw-0.1.4.dist-info/WHEEL
sqlraw-0.1.4.dist-info/METADATA
sqlraw-0.1.4.dist-info/RECORD
