Metadata-Version: 2.1
Name: sqlraw
Version: 0.1.4
Summary: Path base SQL Query
Home-page: https://github.com/developerkitchentr/sqlraw
Author: Uygun Bodur
Author-email: uygun@dop.com.tr
Requires-Python: >=3.10,<4.0
Classifier: Programming Language :: Python :: 3
Classifier: Programming Language :: Python :: 3.10
Requires-Dist: SQLAlchemy (>=2.0.3,<3.0.0)
Requires-Dist: psycopg2 (>=2.9.3,<3.0.0)
Requires-Dist: redis (>=4.2.2,<5.0.0)
Project-URL: Repository, https://github.com/developerkitchentr/sqlraw
